setup.cfg
setup.py
src/dbez/ConnThread.py
src/dbez/Connector.py
src/dbez/Table.py
src/dbez/__init__.py
src/dbez/db_funcs.py
src/dbez/sql_types.py
src/dbez/test.py
src/dbez.egg-info/PKG-INFO
src/dbez.egg-info/SOURCES.txt
src/dbez.egg-info/dependency_links.txt
src/dbez.egg-info/requires.txt
src/dbez.egg-info/top_level.txt
src/dbez/bp_component/__init__.py
src/dbez/errors/__init__.py
src/dbez/errors/decorators.py
src/dbez/errors/errors.py
src/dbez/lib/__init__.py
src/dbez/models/__init__.py
src/dbez/models/page.py
src/dbez/tests/__init__.py