Metadata-Version: 2.1
Name: dbez
Version: 0.1
Summary: Python module for for working with databases of different types
Home-page: https://github.com/Nikit0ska/dbez
Author: nikit0ska
Author-email: nik.ryabov.2014@mail.ru
License: MIT License
Download-URL: https://github.com/Nikit0ska/dbez/archive/refs/heads/main.zip
Platform: UNKNOWN
Classifier: License :: OSI Approved :: Apache Software License
Classifier: Operating System :: OS Independent
Classifier: Intended Audience :: End Users/Desktop
Classifier: Intended Audience :: Developers
Classifier: Programming Language :: Python
Classifier: Programming Language :: Python :: 3
Classifier: Programming Language :: Python :: 3.6
Classifier: Programming Language :: Python :: 3.7
Classifier: Programming Language :: Python :: 3.8
Classifier: Programming Language :: Python :: Implementation :: PyPy
Classifier: Programming Language :: Python :: Implementation :: CPython
